{
  "power_tools_links": [
    {
      "text": "ladders, step stools & work platforms",
      "href": "products.aspx?c=91"
    },
    {
      "text": "toolboxes, tool bags & work benches",
      "href": "products.aspx?c=92"
    },
    {
      "text": "cleaning tools",
      "href": "products.aspx?c=29"
    },
    {
      "text": "electrical & lighting",
      "href": "category.aspx?c=10"
    },
    {
      "text": "batteries & portable power stations",
      "href": "products.aspx?c=96"
    },
    {
      "text": "electrical accessories",
      "href": "products.aspx?c=48"
    },
    {
      "text": "hand tools",
      "href": "category.aspx?c=14"
    },
    {
      "text": "hand tool sets & accessory kits",
      "href": "products.aspx?c=151"
    },
    {
      "text": "automotive tools",
      "href": "products.aspx?c=179"
    },
    {
      "text": "construction tools",
      "href": "products.aspx?c=128"
    },
    {
      "text": "cutting & sawing tools",
      "href": "products.aspx?c=86"
    },
    {
      "text": "electrician tools",
      "href": "products.aspx?c=87"
    },
    {
      "text": "hex tools & accessories",
      "href": "products.aspx?c=176"
    },
    {
      "text": "measuring & layout tools",
      "href": "products.aspx?c=89"
    },
    {
      "text": "multitools & knives",
      "href": "products.aspx?c=123"
    },
    {
      "text": "non sparking safety tools",
      "href": "products.aspx?c=167"
    },
    {
      "text": "plumbing tools",
      "href": "products.aspx?c=152"
    },
    {
      "text": "other hand tools",
      "href": "products.aspx?c=90"
    },
    {
      "text": "power tools - accessories",
      "href": "category.aspx?c=9"
    },
    {
      "text": "powertool batteries & chargers",
      "href": "products.aspx?c=80"
    },
    {
      "text": "multitool accessories",
      "href": "products.aspx?c=187"
    },
    {
      "text": "drilling & fastening accessories",
      "href": "products.aspx?c=79"
    },
    {
      "text": "cutting & sawing accessories",
      "href": "products.aspx?c=81"
    },
    {
      "text": "other power tools accessories",
      "href": "products.aspx?c=84"
    },
    {
      "text": "power tools - corded",
      "href": "category.aspx?c=1"
    },
    {
      "text": "corded drills, impact drivers & wrenches",
      "href": "products.aspx?c=40"
    },
    {
      "text": "corded cutters & saws",
      "href": "products.aspx?c=42"
    },
    {
      "text": "corded grinders",
      "href": "products.aspx?c=41"
    },
    {
      "text": "corded oscillating & rotary powertools",
      "href": "products.aspx?c=166"
    },
    {
      "text": "corded 110v powertools",
      "href": "products.aspx?c=178"
    },
    {
      "text": "other corded power tools",
      "href": "products.aspx?c=45"
    },
    {
      "text": "power tools - cordless",
      "href": "category.aspx?c=50"
    },
    {
      "text": "cordless drills, impact drivers & wrenches",
      "href": "products.aspx?c=51"
    },
    {
      "text": "cordless cutters & saws",
      "href": "products.aspx?c=53"
    },
    {
      "text": "cordless grinders",
      "href": "products.aspx?c=77"
    },
    {
      "text": "other cordless power tools",
      "href": "products.aspx?c=56"
    },
    {
      "text": "lawn mowers & outdoor power tools",
      "href": "products.aspx?c=114"
    },
    {
      "text": "garden tools",
      "href": "products.aspx?c=93"
    },
    {
      "text": "paint brushes, paint rollers & painting tools",
      "href": "products.aspx?c=95"
    },
    {
      "text": "cutting & sawing machines",
      "href": "products.aspx?c=101"
    },
    {
      "text": "drilling machines",
      "href": "products.aspx?c=99"
    },
    {
      "text": "sanding & grinding machines",
      "href": "products.aspx?c=100"
    },
    {
      "text": "pneumatic tool & accessories",
      "href": "category.aspx?c=4"
    },
    {
      "text": "air tools",
      "href": "products.aspx?c=94"
    },
    {
      "text": "electrical & electronic testers",
      "href": "products.aspx?c=173"
    }
  ],
  "total_links_found": 222
}